{
  "version": 2,
  "code": "49010",
  "name": "富士フイルムホールディングス",
  "market": "東証P",
  "sector": "化学",
  "header": {
    "price": 3513,
    "change": 77,
    "changePct": 2.2,
    "isStopHigh": false,
    "turnoverPct": 0.4,
    "marketCap": 4369740547392,
    "appearCount": 0,
    "stopHighCount": 0
  },
  "rows": [
    {
      "date": "2026-04-15",
      "o": 3110,
      "h": 3160,
      "l": 3109,
      "c": 3144,
      "v": 4784300,
      "ma5": 3120.4,
      "ma25": 3048.7,
      "ma75": 3139.6,
      "ma200": 3297.4
    },
    {
      "date": "2026-04-16",
      "o": 3180,
      "h": 3205,
      "l": 3169,
      "c": 3183,
      "v": 4672700,
      "ma5": 3134.0,
      "ma25": 3052.8,
      "ma75": 3137.0,
      "ma200": 3297.9
    },
    {
      "date": "2026-04-17",
      "o": 3172,
      "h": 3203,
      "l": 3166,
      "c": 3166,
      "v": 3624100,
      "ma5": 3144.0,
      "ma25": 3057.2,
      "ma75": 3134.0,
      "ma200": 3298.4
    },
    {
      "date": "2026-04-20",
      "o": 3190,
      "h": 3216,
      "l": 3173,
      "c": 3180,
      "v": 3422300,
      "ma5": 3156.4,
      "ma25": 3063.9,
      "ma75": 3131.3,
      "ma200": 3299.0
    },
    {
      "date": "2026-04-21",
      "o": 3173,
      "h": 3174,
      "l": 3097,
      "c": 3103,
      "v": 3717800,
      "ma5": 3155.2,
      "ma25": 3067.8,
      "ma75": 3127.7,
      "ma200": 3298.9
    },
    {
      "date": "2026-04-22",
      "o": 3073,
      "h": 3094,
      "l": 3050,
      "c": 3061,
      "v": 3316400,
      "ma5": 3138.6,
      "ma25": 3071.2,
      "ma75": 3123.7,
      "ma200": 3298.6
    },
    {
      "date": "2026-04-23",
      "o": 3050,
      "h": 3051,
      "l": 2986,
      "c": 2986,
      "v": 4546100,
      "ma5": 3099.1,
      "ma25": 3068.9,
      "ma75": 3118.9,
      "ma200": 3297.8
    },
    {
      "date": "2026-04-24",
      "o": 2930,
      "h": 2942,
      "l": 2875,
      "c": 2896,
      "v": 9138400,
      "ma5": 3045.1,
      "ma25": 3066.9,
      "ma75": 3112.2,
      "ma200": 3296.6
    },
    {
      "date": "2026-04-27",
      "o": 2896,
      "h": 2912,
      "l": 2880,
      "c": 2880,
      "v": 5513900,
      "ma5": 2985.0,
      "ma25": 3066.4,
      "ma75": 3105.5,
      "ma200": 3295.7
    },
    {
      "date": "2026-04-28",
      "o": 2925,
      "h": 2958,
      "l": 2910,
      "c": 2932,
      "v": 5072500,
      "ma5": 2950.9,
      "ma25": 3065.9,
      "ma75": 3100.0,
      "ma200": 3295.1
    },
    {
      "date": "2026-04-30",
      "o": 2938,
      "h": 2949,
      "l": 2871,
      "c": 2890,
      "v": 7341100,
      "ma5": 2916.7,
      "ma25": 3062.5,
      "ma75": 3094.2,
      "ma200": 3294.1
    },
    {
      "date": "2026-05-01",
      "o": 2876,
      "h": 2918,
      "l": 2870,
      "c": 2876,
      "v": 3634400,
      "ma5": 2894.7,
      "ma25": 3057.5,
      "ma75": 3088.6,
      "ma200": 3293.0
    },
    {
      "date": "2026-05-07",
      "o": 2871,
      "h": 2954,
      "l": 2855,
      "c": 2934,
      "v": 9765200,
      "ma5": 2902.3,
      "ma25": 3054.4,
      "ma75": 3083.2,
      "ma200": 3292.6
    },
    {
      "date": "2026-05-08",
      "o": 2954,
      "h": 3036,
      "l": 2924,
      "c": 3023,
      "v": 8417800,
      "ma5": 2931.0,
      "ma25": 3058.2,
      "ma75": 3077.7,
      "ma200": 3292.5
    },
    {
      "date": "2026-05-11",
      "o": 3060,
      "h": 3086,
      "l": 3042,
      "c": 3055,
      "v": 5860400,
      "ma5": 2955.5,
      "ma25": 3061.7,
      "ma75": 3072.5,
      "ma200": 3292.6
    },
    {
      "date": "2026-05-12",
      "o": 3073,
      "h": 3344,
      "l": 3030,
      "c": 3300,
      "v": 15217100,
      "ma5": 3037.5,
      "ma25": 3070.6,
      "ma75": 3070.6,
      "ma200": 3294.1
    },
    {
      "date": "2026-05-13",
      "o": 3330,
      "h": 3373,
      "l": 3228,
      "c": 3282,
      "v": 9668000,
      "ma5": 3118.8,
      "ma25": 3078.1,
      "ma75": 3069.1,
      "ma200": 3295.5
    },
    {
      "date": "2026-05-14",
      "o": 3212,
      "h": 3257,
      "l": 3200,
      "c": 3226,
      "v": 8213400,
      "ma5": 3177.2,
      "ma25": 3082.7,
      "ma75": 3068.0,
      "ma200": 3296.6
    },
    {
      "date": "2026-05-15",
      "o": 3215,
      "h": 3251,
      "l": 3094,
      "c": 3110,
      "v": 8770700,
      "ma5": 3194.6,
      "ma25": 3081.6,
      "ma75": 3066.2,
      "ma200": 3297.2
    },
    {
      "date": "2026-05-18",
      "o": 3150,
      "h": 3178,
      "l": 3101,
      "c": 3148,
      "v": 4548600,
      "ma5": 3213.2,
      "ma25": 3081.5,
      "ma75": 3065.3,
      "ma200": 3298.0
    },
    {
      "date": "2026-05-19",
      "o": 3198,
      "h": 3198,
      "l": 3150,
      "c": 3171,
      "v": 4253000,
      "ma5": 3187.4,
      "ma25": 3080.1,
      "ma75": 3064.3,
      "ma200": 3298.7
    },
    {
      "date": "2026-05-20",
      "o": 3175,
      "h": 3205,
      "l": 3118,
      "c": 3143,
      "v": 4303900,
      "ma5": 3159.6,
      "ma25": 3081.2,
      "ma75": 3063.9,
      "ma200": 3299.4
    },
    {
      "date": "2026-05-21",
      "o": 3149,
      "h": 3196,
      "l": 3147,
      "c": 3196,
      "v": 3212700,
      "ma5": 3153.6,
      "ma25": 3084.4,
      "ma75": 3064.9,
      "ma200": 3300.5
    },
    {
      "date": "2026-05-22",
      "o": 3148,
      "h": 3195,
      "l": 3131,
      "c": 3181,
      "v": 4339300,
      "ma5": 3167.8,
      "ma25": 3087.0,
      "ma75": 3066.5,
      "ma200": 3301.0
    },
    {
      "date": "2026-05-25",
      "o": 3188,
      "h": 3200,
      "l": 3138,
      "c": 3194,
      "v": 3598500,
      "ma5": 3177.0,
      "ma25": 3090.4,
      "ma75": 3068.4,
      "ma200": 3300.9
    },
    {
      "date": "2026-05-26",
      "o": 3184,
      "h": 3185,
      "l": 3135,
      "c": 3155,
      "v": 3265800,
      "ma5": 3173.8,
      "ma25": 3090.8,
      "ma75": 3069.3,
      "ma200": 3300.8
    },
    {
      "date": "2026-05-27",
      "o": 3200,
      "h": 3368,
      "l": 3196,
      "c": 3224,
      "v": 5523800,
      "ma5": 3190.0,
      "ma25": 3092.4,
      "ma75": 3070.7,
      "ma200": 3300.9
    },
    {
      "date": "2026-05-28",
      "o": 3251,
      "h": 3373,
      "l": 3249,
      "c": 3322,
      "v": 7448400,
      "ma5": 3215.2,
      "ma25": 3098.7,
      "ma75": 3073.1,
      "ma200": 3301.8
    },
    {
      "date": "2026-05-29",
      "o": 3350,
      "h": 3393,
      "l": 3322,
      "c": 3322,
      "v": 8349900,
      "ma5": 3243.4,
      "ma25": 3104.4,
      "ma75": 3075.7,
      "ma200": 3302.6
    },
    {
      "date": "2026-06-01",
      "o": 3350,
      "h": 3407,
      "l": 3278,
      "c": 3381,
      "v": 6094800,
      "ma5": 3280.8,
      "ma25": 3115.5,
      "ma75": 3079.2,
      "ma200": 3303.8
    },
    {
      "date": "2026-06-02",
      "o": 3390,
      "h": 3392,
      "l": 3325,
      "c": 3346,
      "v": 6815500,
      "ma5": 3319.0,
      "ma25": 3126.9,
      "ma75": 3083.5,
      "ma200": 3304.7
    },
    {
      "date": "2026-06-03",
      "o": 3410,
      "h": 3482,
      "l": 3390,
      "c": 3479,
      "v": 6810500,
      "ma5": 3370.0,
      "ma25": 3146.6,
      "ma75": 3089.2,
      "ma200": 3306.6
    },
    {
      "date": "2026-06-04",
      "o": 3442,
      "h": 3548,
      "l": 3435,
      "c": 3548,
      "v": 6512200,
      "ma5": 3415.2,
      "ma25": 3172.7,
      "ma75": 3095.8,
      "ma200": 3308.7
    },
    {
      "date": "2026-06-05",
      "o": 3547,
      "h": 3547,
      "l": 3480,
      "c": 3528,
      "v": 4799900,
      "ma5": 3456.4,
      "ma25": 3198.6,
      "ma75": 3102.1,
      "ma200": 3310.2
    },
    {
      "date": "2026-06-08",
      "o": 3458,
      "h": 3524,
      "l": 3399,
      "c": 3426,
      "v": 8005300,
      "ma5": 3465.4,
      "ma25": 3218.4,
      "ma75": 3107.3,
      "ma200": 3310.6
    },
    {
      "date": "2026-06-09",
      "o": 3486,
      "h": 3504,
      "l": 3452,
      "c": 3504,
      "v": 5806500,
      "ma5": 3497.0,
      "ma25": 3242.9,
      "ma75": 3113.2,
      "ma200": 3310.7
    },
    {
      "date": "2026-06-10",
      "o": 3515,
      "h": 3573,
      "l": 3478,
      "c": 3521,
      "v": 5363300,
      "ma5": 3505.4,
      "ma25": 3268.8,
      "ma75": 3119.1,
      "ma200": 3310.7
    },
    {
      "date": "2026-06-11",
      "o": 3509,
      "h": 3532,
      "l": 3459,
      "c": 3485,
      "v": 4663800,
      "ma5": 3492.8,
      "ma25": 3290.8,
      "ma75": 3123.6,
      "ma200": 3310.3
    },
    {
      "date": "2026-06-12",
      "o": 3526,
      "h": 3537,
      "l": 3390,
      "c": 3401,
      "v": 6372700,
      "ma5": 3467.4,
      "ma25": 3305.9,
      "ma75": 3128.3,
      "ma200": 3309.6
    },
    {
      "date": "2026-06-15",
      "o": 3423,
      "h": 3441,
      "l": 3371,
      "c": 3439,
      "v": 6308500,
      "ma5": 3470.0,
      "ma25": 3321.3,
      "ma75": 3134.1,
      "ma200": 3308.8
    },
    {
      "date": "2026-06-16",
      "o": 3398,
      "h": 3464,
      "l": 3371,
      "c": 3379,
      "v": 4296800,
      "ma5": 3445.0,
      "ma25": 3324.4,
      "ma75": 3139.3,
      "ma200": 3307.7
    },
    {
      "date": "2026-06-17",
      "o": 3381,
      "h": 3407,
      "l": 3334,
      "c": 3377,
      "v": 3633700,
      "ma5": 3416.2,
      "ma25": 3328.2,
      "ma75": 3143.8,
      "ma200": 3306.5
    },
    {
      "date": "2026-06-18",
      "o": 3388,
      "h": 3449,
      "l": 3384,
      "c": 3424,
      "v": 4322700,
      "ma5": 3404.0,
      "ma25": 3336.2,
      "ma75": 3147.0,
      "ma200": 3305.8
    },
    {
      "date": "2026-06-19",
      "o": 3494,
      "h": 3495,
      "l": 3363,
      "c": 3383,
      "v": 6659100,
      "ma5": 3400.4,
      "ma25": 3347.1,
      "ma75": 3148.8,
      "ma200": 3305.1
    },
    {
      "date": "2026-06-22",
      "o": 3380,
      "h": 3429,
      "l": 3364,
      "c": 3364,
      "v": 2785500,
      "ma5": 3385.4,
      "ma25": 3355.7,
      "ma75": 3151.4,
      "ma200": 3303.9
    },
    {
      "date": "2026-06-23",
      "o": 3350,
      "h": 3373,
      "l": 3320,
      "c": 3320,
      "v": 4392400,
      "ma5": 3373.6,
      "ma25": 3361.7,
      "ma75": 3154.8,
      "ma200": 3302.5
    },
    {
      "date": "2026-06-24",
      "o": 3311,
      "h": 3367,
      "l": 3304,
      "c": 3333,
      "v": 3750100,
      "ma5": 3364.8,
      "ma25": 3369.3,
      "ma75": 3159.6,
      "ma200": 3301.2
    },
    {
      "date": "2026-06-25",
      "o": 3370,
      "h": 3425,
      "l": 3353,
      "c": 3413,
      "v": 3594100,
      "ma5": 3362.6,
      "ma25": 3378.0,
      "ma75": 3165.2,
      "ma200": 3300.5
    },
    {
      "date": "2026-06-26",
      "o": 3399,
      "h": 3469,
      "l": 3397,
      "c": 3436,
      "v": 5047100,
      "ma5": 3373.2,
      "ma25": 3388.2,
      "ma75": 3171.0,
      "ma200": 3300.0
    },
    {
      "date": "2026-06-29",
      "o": 3418,
      "h": 3515,
      "l": 3413,
      "c": 3513,
      "v": 4914400,
      "ma5": 3403.0,
      "ma25": 3400.9,
      "ma75": 3178.3,
      "ma200": 3300.0
    }
  ]
}