{
  "version": 2,
  "code": "52570",
  "name": "ノバシステム",
  "market": "東証S",
  "sector": "情報･通信業",
  "header": {
    "price": 2550,
    "change": -8,
    "changePct": -0.3,
    "isStopHigh": false,
    "turnoverPct": 0.0,
    "marketCap": 3576375000,
    "appearCount": 0,
    "stopHighCount": 0
  },
  "rows": [
    {
      "date": "2026-04-17",
      "o": 2580,
      "h": 2586,
      "l": 2562,
      "c": 2562,
      "v": 600,
      "ma5": 2561.6,
      "ma25": 2477.5,
      "ma75": 2564.6,
      "ma200": null
    },
    {
      "date": "2026-04-20",
      "o": 2587,
      "h": 2613,
      "l": 2580,
      "c": 2613,
      "v": 2200,
      "ma5": 2577.0,
      "ma25": 2484.4,
      "ma75": 2561.6,
      "ma200": null
    },
    {
      "date": "2026-04-21",
      "o": 2613,
      "h": 2650,
      "l": 2587,
      "c": 2619,
      "v": 4100,
      "ma5": 2587.4,
      "ma25": 2490.9,
      "ma75": 2559.5,
      "ma200": null
    },
    {
      "date": "2026-04-22",
      "o": 2639,
      "h": 2639,
      "l": 2581,
      "c": 2583,
      "v": 8400,
      "ma5": 2592.6,
      "ma25": 2496.4,
      "ma75": 2557.4,
      "ma200": null
    },
    {
      "date": "2026-04-23",
      "o": 2583,
      "h": 2612,
      "l": 2579,
      "c": 2579,
      "v": 2100,
      "ma5": 2591.2,
      "ma25": 2501.8,
      "ma75": 2554.5,
      "ma200": null
    },
    {
      "date": "2026-04-24",
      "o": 2579,
      "h": 2580,
      "l": 2570,
      "c": 2575,
      "v": 3100,
      "ma5": 2593.8,
      "ma25": 2508.4,
      "ma75": 2551.6,
      "ma200": null
    },
    {
      "date": "2026-04-27",
      "o": 2582,
      "h": 2584,
      "l": 2571,
      "c": 2574,
      "v": 1300,
      "ma5": 2586.0,
      "ma25": 2516.1,
      "ma75": 2548.7,
      "ma200": null
    },
    {
      "date": "2026-04-28",
      "o": 2574,
      "h": 2586,
      "l": 2571,
      "c": 2575,
      "v": 3000,
      "ma5": 2577.2,
      "ma25": 2523.0,
      "ma75": 2545.7,
      "ma200": null
    },
    {
      "date": "2026-04-30",
      "o": 2577,
      "h": 2616,
      "l": 2400,
      "c": 2500,
      "v": 27000,
      "ma5": 2560.6,
      "ma25": 2526.0,
      "ma75": 2541.5,
      "ma200": null
    },
    {
      "date": "2026-05-01",
      "o": 2510,
      "h": 2549,
      "l": 2470,
      "c": 2470,
      "v": 3500,
      "ma5": 2538.8,
      "ma25": 2527.8,
      "ma75": 2536.9,
      "ma200": null
    },
    {
      "date": "2026-05-07",
      "o": 2487,
      "h": 2509,
      "l": 2482,
      "c": 2487,
      "v": 3900,
      "ma5": 2521.2,
      "ma25": 2530.1,
      "ma75": 2532.2,
      "ma200": null
    },
    {
      "date": "2026-05-08",
      "o": 2482,
      "h": 2482,
      "l": 2459,
      "c": 2470,
      "v": 1300,
      "ma5": 2500.4,
      "ma25": 2532.9,
      "ma75": 2527.7,
      "ma200": null
    },
    {
      "date": "2026-05-11",
      "o": 2467,
      "h": 2489,
      "l": 2464,
      "c": 2465,
      "v": 1800,
      "ma5": 2478.4,
      "ma25": 2533.5,
      "ma75": 2523.2,
      "ma200": null
    },
    {
      "date": "2026-05-12",
      "o": 2465,
      "h": 2470,
      "l": 2443,
      "c": 2467,
      "v": 1900,
      "ma5": 2471.8,
      "ma25": 2533.8,
      "ma75": 2518.5,
      "ma200": null
    },
    {
      "date": "2026-05-13",
      "o": 2476,
      "h": 2476,
      "l": 2432,
      "c": 2432,
      "v": 1300,
      "ma5": 2464.2,
      "ma25": 2533.2,
      "ma75": 2513.2,
      "ma200": null
    },
    {
      "date": "2026-05-14",
      "o": 2382,
      "h": 2410,
      "l": 2382,
      "c": 2384,
      "v": 7400,
      "ma5": 2443.6,
      "ma25": 2530.4,
      "ma75": 2507.2,
      "ma200": null
    },
    {
      "date": "2026-05-15",
      "o": 2373,
      "h": 2375,
      "l": 2352,
      "c": 2375,
      "v": 5900,
      "ma5": 2424.6,
      "ma25": 2525.6,
      "ma75": 2501.5,
      "ma200": null
    },
    {
      "date": "2026-05-18",
      "o": 2378,
      "h": 2378,
      "l": 2315,
      "c": 2315,
      "v": 7800,
      "ma5": 2394.6,
      "ma25": 2517.4,
      "ma75": 2495.0,
      "ma200": null
    },
    {
      "date": "2026-05-19",
      "o": 2365,
      "h": 2365,
      "l": 2350,
      "c": 2350,
      "v": 3600,
      "ma5": 2371.2,
      "ma25": 2510.6,
      "ma75": 2489.2,
      "ma200": null
    },
    {
      "date": "2026-05-20",
      "o": 2379,
      "h": 2380,
      "l": 2350,
      "c": 2380,
      "v": 5600,
      "ma5": 2360.8,
      "ma25": 2503.9,
      "ma75": 2484.6,
      "ma200": null
    },
    {
      "date": "2026-05-21",
      "o": 2426,
      "h": 2549,
      "l": 2400,
      "c": 2486,
      "v": 10200,
      "ma5": 2381.2,
      "ma25": 2500.3,
      "ma75": 2481.1,
      "ma200": null
    },
    {
      "date": "2026-05-22",
      "o": 2466,
      "h": 2484,
      "l": 2455,
      "c": 2475,
      "v": 3400,
      "ma5": 2401.2,
      "ma25": 2497.8,
      "ma75": 2478.2,
      "ma200": null
    },
    {
      "date": "2026-05-25",
      "o": 2480,
      "h": 2521,
      "l": 2479,
      "c": 2479,
      "v": 4200,
      "ma5": 2434.0,
      "ma25": 2494.3,
      "ma75": 2475.9,
      "ma200": null
    },
    {
      "date": "2026-05-26",
      "o": 2544,
      "h": 2594,
      "l": 2521,
      "c": 2588,
      "v": 9400,
      "ma5": 2481.6,
      "ma25": 2495.6,
      "ma75": 2475.5,
      "ma200": null
    },
    {
      "date": "2026-05-27",
      "o": 2609,
      "h": 2609,
      "l": 2575,
      "c": 2577,
      "v": 4300,
      "ma5": 2521.0,
      "ma25": 2495.2,
      "ma75": 2473.9,
      "ma200": null
    },
    {
      "date": "2026-05-28",
      "o": 2598,
      "h": 2598,
      "l": 2551,
      "c": 2560,
      "v": 2300,
      "ma5": 2535.8,
      "ma25": 2495.1,
      "ma75": 2471.4,
      "ma200": null
    },
    {
      "date": "2026-05-29",
      "o": 2560,
      "h": 2563,
      "l": 2557,
      "c": 2560,
      "v": 1300,
      "ma5": 2552.8,
      "ma25": 2493.0,
      "ma75": 2469.5,
      "ma200": null
    },
    {
      "date": "2026-06-01",
      "o": 2588,
      "h": 2588,
      "l": 2551,
      "c": 2551,
      "v": 2500,
      "ma5": 2567.2,
      "ma25": 2490.3,
      "ma75": 2468.2,
      "ma200": null
    },
    {
      "date": "2026-06-02",
      "o": 2538,
      "h": 2570,
      "l": 2538,
      "c": 2541,
      "v": 900,
      "ma5": 2557.8,
      "ma25": 2488.6,
      "ma75": 2467.3,
      "ma200": null
    },
    {
      "date": "2026-06-03",
      "o": 2524,
      "h": 2549,
      "l": 2512,
      "c": 2549,
      "v": 2500,
      "ma5": 2552.2,
      "ma25": 2487.4,
      "ma75": 2467.8,
      "ma200": null
    },
    {
      "date": "2026-06-04",
      "o": 2525,
      "h": 2547,
      "l": 2455,
      "c": 2455,
      "v": 3800,
      "ma5": 2531.2,
      "ma25": 2482.6,
      "ma75": 2466.7,
      "ma200": null
    },
    {
      "date": "2026-06-05",
      "o": 2433,
      "h": 2462,
      "l": 2433,
      "c": 2462,
      "v": 800,
      "ma5": 2511.6,
      "ma25": 2478.1,
      "ma75": 2465.3,
      "ma200": null
    },
    {
      "date": "2026-06-08",
      "o": 2412,
      "h": 2460,
      "l": 2411,
      "c": 2460,
      "v": 1300,
      "ma5": 2493.4,
      "ma25": 2473.5,
      "ma75": 2465.6,
      "ma200": null
    },
    {
      "date": "2026-06-09",
      "o": 2455,
      "h": 2458,
      "l": 2433,
      "c": 2433,
      "v": 1500,
      "ma5": 2471.8,
      "ma25": 2470.8,
      "ma75": 2466.9,
      "ma200": null
    },
    {
      "date": "2026-06-10",
      "o": 2448,
      "h": 2457,
      "l": 2448,
      "c": 2457,
      "v": 500,
      "ma5": 2453.4,
      "ma25": 2470.3,
      "ma75": 2468.1,
      "ma200": null
    },
    {
      "date": "2026-06-11",
      "o": 2457,
      "h": 2457,
      "l": 2430,
      "c": 2440,
      "v": 1900,
      "ma5": 2450.4,
      "ma25": 2468.4,
      "ma75": 2469.6,
      "ma200": null
    },
    {
      "date": "2026-06-12",
      "o": 2460,
      "h": 2486,
      "l": 2450,
      "c": 2486,
      "v": 1100,
      "ma5": 2455.2,
      "ma25": 2469.1,
      "ma75": 2471.9,
      "ma200": null
    },
    {
      "date": "2026-06-15",
      "o": 2493,
      "h": 2500,
      "l": 2493,
      "c": 2497,
      "v": 1200,
      "ma5": 2462.6,
      "ma25": 2470.4,
      "ma75": 2473.9,
      "ma200": null
    },
    {
      "date": "2026-06-16",
      "o": 2515,
      "h": 2521,
      "l": 2510,
      "c": 2519,
      "v": 5100,
      "ma5": 2479.8,
      "ma25": 2472.4,
      "ma75": 2475.7,
      "ma200": null
    },
    {
      "date": "2026-06-17",
      "o": 2530,
      "h": 2542,
      "l": 2529,
      "c": 2542,
      "v": 1000,
      "ma5": 2496.8,
      "ma25": 2476.8,
      "ma75": 2478.4,
      "ma200": null
    },
    {
      "date": "2026-06-18",
      "o": 2542,
      "h": 2542,
      "l": 2515,
      "c": 2516,
      "v": 500,
      "ma5": 2512.0,
      "ma25": 2482.1,
      "ma75": 2480.4,
      "ma200": null
    },
    {
      "date": "2026-06-19",
      "o": 2495,
      "h": 2512,
      "l": 2484,
      "c": 2486,
      "v": 1200,
      "ma5": 2512.0,
      "ma25": 2486.6,
      "ma75": 2481.2,
      "ma200": null
    },
    {
      "date": "2026-06-22",
      "o": 2562,
      "h": 2562,
      "l": 2483,
      "c": 2483,
      "v": 2700,
      "ma5": 2509.2,
      "ma25": 2493.3,
      "ma75": 2481.3,
      "ma200": null
    },
    {
      "date": "2026-06-23",
      "o": 2483,
      "h": 2485,
      "l": 2479,
      "c": 2479,
      "v": 900,
      "ma5": 2501.2,
      "ma25": 2498.4,
      "ma75": 2482.5,
      "ma200": null
    },
    {
      "date": "2026-06-24",
      "o": 2466,
      "h": 2466,
      "l": 2459,
      "c": 2459,
      "v": 300,
      "ma5": 2484.6,
      "ma25": 2501.6,
      "ma75": 2483.6,
      "ma200": null
    },
    {
      "date": "2026-06-25",
      "o": 2460,
      "h": 2500,
      "l": 2460,
      "c": 2500,
      "v": 200,
      "ma5": 2481.4,
      "ma25": 2502.2,
      "ma75": 2484.5,
      "ma200": null
    },
    {
      "date": "2026-06-26",
      "o": 2474,
      "h": 2474,
      "l": 2414,
      "c": 2461,
      "v": 1600,
      "ma5": 2476.4,
      "ma25": 2501.6,
      "ma75": 2484.9,
      "ma200": null
    },
    {
      "date": "2026-06-29",
      "o": 2461,
      "h": 2611,
      "l": 2461,
      "c": 2499,
      "v": 1700,
      "ma5": 2479.6,
      "ma25": 2502.4,
      "ma75": 2486.4,
      "ma200": null
    },
    {
      "date": "2026-06-30",
      "o": 2540,
      "h": 2558,
      "l": 2539,
      "c": 2558,
      "v": 900,
      "ma5": 2495.4,
      "ma25": 2501.2,
      "ma75": 2487.9,
      "ma200": null
    },
    {
      "date": "2026-07-01",
      "o": 2580,
      "h": 2580,
      "l": 2550,
      "c": 2550,
      "v": 600,
      "ma5": 2513.6,
      "ma25": 2500.1,
      "ma75": 2489.3,
      "ma200": null
    }
  ]
}