{
  "version": 2,
  "code": "61960",
  "name": "ストライクグループ",
  "market": "東証P",
  "sector": "サービス業",
  "header": {
    "price": 1257,
    "change": -6,
    "changePct": -0.5,
    "isStopHigh": false,
    "turnoverPct": 0.4,
    "marketCap": 72414513000,
    "appearCount": 2,
    "stopHighCount": 0
  },
  "rows": [
    {
      "date": "2026-04-16",
      "o": 1504,
      "h": 1524,
      "l": 1479,
      "c": 1485,
      "v": 241000,
      "ma5": 1460.8,
      "ma25": 2552.0,
      "ma75": 3657.3,
      "ma200": 3927.2
    },
    {
      "date": "2026-04-17",
      "o": 1480,
      "h": 1498,
      "l": 1457,
      "c": 1457,
      "v": 216300,
      "ma5": 1469.0,
      "ma25": 2447.3,
      "ma75": 3622.4,
      "ma200": 3916.6
    },
    {
      "date": "2026-04-20",
      "o": 1465,
      "h": 1465,
      "l": 1388,
      "c": 1418,
      "v": 399700,
      "ma5": 1465.8,
      "ma25": 2339.6,
      "ma75": 3586.3,
      "ma200": 3905.6
    },
    {
      "date": "2026-04-21",
      "o": 1448,
      "h": 1449,
      "l": 1399,
      "c": 1402,
      "v": 247500,
      "ma5": 1451.8,
      "ma25": 2234.9,
      "ma75": 3549.6,
      "ma200": 3894.4
    },
    {
      "date": "2026-04-22",
      "o": 1423,
      "h": 1429,
      "l": 1400,
      "c": 1420,
      "v": 272300,
      "ma5": 1436.4,
      "ma25": 2130.1,
      "ma75": 3512.8,
      "ma200": 3883.5
    },
    {
      "date": "2026-04-23",
      "o": 1440,
      "h": 1448,
      "l": 1416,
      "c": 1443,
      "v": 312900,
      "ma5": 1428.0,
      "ma25": 2024.6,
      "ma75": 3477.1,
      "ma200": 3872.4
    },
    {
      "date": "2026-04-24",
      "o": 1263,
      "h": 1299,
      "l": 1196,
      "c": 1217,
      "v": 2543400,
      "ma5": 1380.0,
      "ma25": 1916.9,
      "ma75": 3438.2,
      "ma200": 3859.9,
      "marks": [
        "appear"
      ]
    },
    {
      "date": "2026-04-27",
      "o": 1238,
      "h": 1263,
      "l": 1226,
      "c": 1258,
      "v": 1229000,
      "ma5": 1348.0,
      "ma25": 1812.8,
      "ma75": 3399.1,
      "ma200": 3847.4
    },
    {
      "date": "2026-04-28",
      "o": 1278,
      "h": 1317,
      "l": 1262,
      "c": 1298,
      "v": 1483500,
      "ma5": 1327.2,
      "ma25": 1708.2,
      "ma75": 3360.1,
      "ma200": 3835.0
    },
    {
      "date": "2026-04-30",
      "o": 1297,
      "h": 1327,
      "l": 1280,
      "c": 1314,
      "v": 895900,
      "ma5": 1306.0,
      "ma25": 1600.7,
      "ma75": 3320.6,
      "ma200": 3823.1
    },
    {
      "date": "2026-05-01",
      "o": 1218,
      "h": 1229,
      "l": 1185,
      "c": 1187,
      "v": 2793900,
      "ma5": 1254.8,
      "ma25": 1492.2,
      "ma75": 3279.5,
      "ma200": 3810.4,
      "marks": [
        "appear"
      ]
    },
    {
      "date": "2026-05-07",
      "o": 1217,
      "h": 1238,
      "l": 1195,
      "c": 1218,
      "v": 891900,
      "ma5": 1255.0,
      "ma25": 1381.9,
      "ma75": 3238.6,
      "ma200": 3797.7
    },
    {
      "date": "2026-05-08",
      "o": 1227,
      "h": 1239,
      "l": 1210,
      "c": 1233,
      "v": 674400,
      "ma5": 1250.0,
      "ma25": 1378.4,
      "ma75": 3198.3,
      "ma200": 3785.0
    },
    {
      "date": "2026-05-11",
      "o": 1235,
      "h": 1241,
      "l": 1207,
      "c": 1214,
      "v": 749600,
      "ma5": 1233.2,
      "ma25": 1372.8,
      "ma75": 3156.9,
      "ma200": 3771.9
    },
    {
      "date": "2026-05-12",
      "o": 1219,
      "h": 1222,
      "l": 1197,
      "c": 1202,
      "v": 494600,
      "ma5": 1210.8,
      "ma25": 1365.1,
      "ma75": 3115.3,
      "ma200": 3758.8
    },
    {
      "date": "2026-05-13",
      "o": 1202,
      "h": 1232,
      "l": 1201,
      "c": 1229,
      "v": 328600,
      "ma5": 1219.2,
      "ma25": 1358.5,
      "ma75": 3074.9,
      "ma200": 3745.9
    },
    {
      "date": "2026-05-14",
      "o": 1213,
      "h": 1240,
      "l": 1204,
      "c": 1236,
      "v": 372400,
      "ma5": 1222.8,
      "ma25": 1352.0,
      "ma75": 3035.0,
      "ma200": 3733.0
    },
    {
      "date": "2026-05-15",
      "o": 1230,
      "h": 1244,
      "l": 1210,
      "c": 1220,
      "v": 250500,
      "ma5": 1220.2,
      "ma25": 1344.4,
      "ma75": 2995.9,
      "ma200": 3720.1
    },
    {
      "date": "2026-05-18",
      "o": 1218,
      "h": 1218,
      "l": 1166,
      "c": 1174,
      "v": 815200,
      "ma5": 1212.2,
      "ma25": 1334.2,
      "ma75": 2955.8,
      "ma200": 3707.3
    },
    {
      "date": "2026-05-19",
      "o": 1197,
      "h": 1223,
      "l": 1190,
      "c": 1212,
      "v": 437500,
      "ma5": 1214.2,
      "ma25": 1323.9,
      "ma75": 2915.2,
      "ma200": 3694.6
    },
    {
      "date": "2026-05-20",
      "o": 1212,
      "h": 1224,
      "l": 1193,
      "c": 1205,
      "v": 402600,
      "ma5": 1209.4,
      "ma25": 1314.4,
      "ma75": 2875.2,
      "ma200": 3681.9
    },
    {
      "date": "2026-05-21",
      "o": 1210,
      "h": 1220,
      "l": 1201,
      "c": 1206,
      "v": 344200,
      "ma5": 1203.4,
      "ma25": 1306.0,
      "ma75": 2835.9,
      "ma200": 3669.1
    },
    {
      "date": "2026-05-22",
      "o": 1210,
      "h": 1244,
      "l": 1210,
      "c": 1230,
      "v": 311900,
      "ma5": 1205.4,
      "ma25": 1297.9,
      "ma75": 2796.9,
      "ma200": 3655.9
    },
    {
      "date": "2026-05-25",
      "o": 1221,
      "h": 1222,
      "l": 1195,
      "c": 1212,
      "v": 386700,
      "ma5": 1213.0,
      "ma25": 1287.5,
      "ma75": 2757.1,
      "ma200": 3642.7
    },
    {
      "date": "2026-05-26",
      "o": 1214,
      "h": 1238,
      "l": 1214,
      "c": 1223,
      "v": 398500,
      "ma5": 1215.2,
      "ma25": 1276.5,
      "ma75": 2717.3,
      "ma200": 3629.1
    },
    {
      "date": "2026-05-27",
      "o": 1232,
      "h": 1239,
      "l": 1214,
      "c": 1237,
      "v": 291000,
      "ma5": 1221.6,
      "ma25": 1266.6,
      "ma75": 2681.1,
      "ma200": 3615.5
    },
    {
      "date": "2026-05-28",
      "o": 1225,
      "h": 1233,
      "l": 1215,
      "c": 1230,
      "v": 330000,
      "ma5": 1226.4,
      "ma25": 1257.5,
      "ma75": 2645.0,
      "ma200": 3602.0
    },
    {
      "date": "2026-05-29",
      "o": 1231,
      "h": 1281,
      "l": 1231,
      "c": 1260,
      "v": 446200,
      "ma5": 1232.4,
      "ma25": 1251.2,
      "ma75": 2609.7,
      "ma200": 3589.0
    },
    {
      "date": "2026-06-01",
      "o": 1270,
      "h": 1276,
      "l": 1242,
      "c": 1247,
      "v": 400100,
      "ma5": 1239.4,
      "ma25": 1245.0,
      "ma75": 2573.6,
      "ma200": 3575.5
    },
    {
      "date": "2026-06-02",
      "o": 1233,
      "h": 1241,
      "l": 1210,
      "c": 1237,
      "v": 429000,
      "ma5": 1242.2,
      "ma25": 1237.7,
      "ma75": 2537.4,
      "ma200": 3561.7
    },
    {
      "date": "2026-06-03",
      "o": 1240,
      "h": 1241,
      "l": 1210,
      "c": 1210,
      "v": 521800,
      "ma5": 1236.8,
      "ma25": 1228.4,
      "ma75": 2500.3,
      "ma200": 3547.7
    },
    {
      "date": "2026-06-04",
      "o": 1210,
      "h": 1223,
      "l": 1194,
      "c": 1218,
      "v": 369500,
      "ma5": 1234.4,
      "ma25": 1228.4,
      "ma75": 2461.2,
      "ma200": 3533.5
    },
    {
      "date": "2026-06-05",
      "o": 1228,
      "h": 1251,
      "l": 1223,
      "c": 1240,
      "v": 395400,
      "ma5": 1230.4,
      "ma25": 1227.7,
      "ma75": 2422.8,
      "ma200": 3519.6
    },
    {
      "date": "2026-06-08",
      "o": 1232,
      "h": 1259,
      "l": 1225,
      "c": 1242,
      "v": 355400,
      "ma5": 1229.4,
      "ma25": 1225.4,
      "ma75": 2385.9,
      "ma200": 3505.7
    },
    {
      "date": "2026-06-09",
      "o": 1248,
      "h": 1266,
      "l": 1243,
      "c": 1250,
      "v": 206900,
      "ma5": 1232.0,
      "ma25": 1222.9,
      "ma75": 2347.8,
      "ma200": 3491.7
    },
    {
      "date": "2026-06-10",
      "o": 1240,
      "h": 1262,
      "l": 1237,
      "c": 1244,
      "v": 229400,
      "ma5": 1238.8,
      "ma25": 1225.2,
      "ma75": 2308.4,
      "ma200": 3477.6
    },
    {
      "date": "2026-06-11",
      "o": 1243,
      "h": 1243,
      "l": 1227,
      "c": 1239,
      "v": 250500,
      "ma5": 1243.0,
      "ma25": 1226.0,
      "ma75": 2267.7,
      "ma200": 3463.3
    },
    {
      "date": "2026-06-12",
      "o": 1269,
      "h": 1269,
      "l": 1241,
      "c": 1262,
      "v": 337700,
      "ma5": 1247.4,
      "ma25": 1227.2,
      "ma75": 2227.1,
      "ma200": 3449.0
    },
    {
      "date": "2026-06-15",
      "o": 1270,
      "h": 1286,
      "l": 1262,
      "c": 1269,
      "v": 217700,
      "ma5": 1252.8,
      "ma25": 1229.4,
      "ma75": 2185.9,
      "ma200": 3434.7
    },
    {
      "date": "2026-06-16",
      "o": 1261,
      "h": 1269,
      "l": 1253,
      "c": 1264,
      "v": 149400,
      "ma5": 1255.6,
      "ma25": 1231.8,
      "ma75": 2145.4,
      "ma200": 3420.0
    },
    {
      "date": "2026-06-17",
      "o": 1283,
      "h": 1287,
      "l": 1263,
      "c": 1265,
      "v": 183400,
      "ma5": 1259.8,
      "ma25": 1233.3,
      "ma75": 2104.2,
      "ma200": 3404.8
    },
    {
      "date": "2026-06-18",
      "o": 1265,
      "h": 1279,
      "l": 1251,
      "c": 1264,
      "v": 184400,
      "ma5": 1264.8,
      "ma25": 1234.4,
      "ma75": 2061.8,
      "ma200": 3389.7
    },
    {
      "date": "2026-06-19",
      "o": 1283,
      "h": 1284,
      "l": 1258,
      "c": 1265,
      "v": 251800,
      "ma5": 1265.4,
      "ma25": 1236.2,
      "ma75": 2017.3,
      "ma200": 3374.8
    },
    {
      "date": "2026-06-22",
      "o": 1277,
      "h": 1310,
      "l": 1271,
      "c": 1274,
      "v": 343800,
      "ma5": 1266.4,
      "ma25": 1240.2,
      "ma75": 1972.8,
      "ma200": 3360.3
    },
    {
      "date": "2026-06-23",
      "o": 1275,
      "h": 1275,
      "l": 1248,
      "c": 1248,
      "v": 305600,
      "ma5": 1263.2,
      "ma25": 1241.6,
      "ma75": 1931.6,
      "ma200": 3345.0
    },
    {
      "date": "2026-06-24",
      "o": 1259,
      "h": 1265,
      "l": 1246,
      "c": 1246,
      "v": 214800,
      "ma5": 1259.4,
      "ma25": 1243.3,
      "ma75": 1893.1,
      "ma200": 3330.1
    },
    {
      "date": "2026-06-25",
      "o": 1255,
      "h": 1260,
      "l": 1245,
      "c": 1247,
      "v": 208800,
      "ma5": 1256.0,
      "ma25": 1244.9,
      "ma75": 1853.4,
      "ma200": 3315.0
    },
    {
      "date": "2026-06-26",
      "o": 1246,
      "h": 1252,
      "l": 1235,
      "c": 1242,
      "v": 208000,
      "ma5": 1251.4,
      "ma25": 1245.4,
      "ma75": 1811.0,
      "ma200": 3299.7
    },
    {
      "date": "2026-06-29",
      "o": 1252,
      "h": 1268,
      "l": 1251,
      "c": 1263,
      "v": 323400,
      "ma5": 1249.2,
      "ma25": 1247.4,
      "ma75": 1771.2,
      "ma200": 3284.4
    },
    {
      "date": "2026-06-30",
      "o": 1269,
      "h": 1275,
      "l": 1256,
      "c": 1257,
      "v": 212500,
      "ma5": 1251.0,
      "ma25": 1248.8,
      "ma75": 1730.0,
      "ma200": 3268.9
    }
  ]
}