{
  "version": 2,
  "code": "63610",
  "name": "荏原製作所",
  "market": "東証P",
  "sector": "機械",
  "header": {
    "price": 6300,
    "change": 44,
    "changePct": 0.7,
    "isStopHigh": false,
    "turnoverPct": 0.8,
    "marketCap": 2880754915500,
    "appearCount": 0,
    "stopHighCount": 0
  },
  "rows": [
    {
      "date": "2026-04-17",
      "o": 5090,
      "h": 5115,
      "l": 4933,
      "c": 4933,
      "v": 2076600,
      "ma5": 5071.2,
      "ma25": 4739.6,
      "ma75": 4865.4,
      "ma200": 3947.8
    },
    {
      "date": "2026-04-20",
      "o": 5070,
      "h": 5185,
      "l": 5050,
      "c": 5131,
      "v": 2190600,
      "ma5": 5080.0,
      "ma25": 4751.5,
      "ma75": 4884.6,
      "ma200": 3961.6
    },
    {
      "date": "2026-04-21",
      "o": 5193,
      "h": 5205,
      "l": 5114,
      "c": 5137,
      "v": 1813400,
      "ma5": 5073.2,
      "ma25": 4769.4,
      "ma75": 4904.2,
      "ma200": 3975.2
    },
    {
      "date": "2026-04-22",
      "o": 5187,
      "h": 5471,
      "l": 5171,
      "c": 5471,
      "v": 4481500,
      "ma5": 5166.6,
      "ma25": 4798.2,
      "ma75": 4927.7,
      "ma200": 3989.2
    },
    {
      "date": "2026-04-23",
      "o": 5390,
      "h": 5400,
      "l": 5223,
      "c": 5309,
      "v": 3450000,
      "ma5": 5196.2,
      "ma25": 4812.0,
      "ma75": 4949.3,
      "ma200": 4002.2
    },
    {
      "date": "2026-04-24",
      "o": 5461,
      "h": 5461,
      "l": 5269,
      "c": 5304,
      "v": 2647100,
      "ma5": 5270.4,
      "ma25": 4834.0,
      "ma75": 4968.2,
      "ma200": 4014.8
    },
    {
      "date": "2026-04-27",
      "o": 5370,
      "h": 5477,
      "l": 5231,
      "c": 5446,
      "v": 2855200,
      "ma5": 5333.4,
      "ma25": 4877.3,
      "ma75": 4986.9,
      "ma200": 4028.1
    },
    {
      "date": "2026-04-28",
      "o": 5515,
      "h": 5563,
      "l": 5422,
      "c": 5423,
      "v": 4089500,
      "ma5": 5390.6,
      "ma25": 4914.7,
      "ma75": 5001.5,
      "ma200": 4041.4
    },
    {
      "date": "2026-04-30",
      "o": 5523,
      "h": 5538,
      "l": 5272,
      "c": 5327,
      "v": 3556400,
      "ma5": 5361.8,
      "ma25": 4933.9,
      "ma75": 5013.8,
      "ma200": 4054.4
    },
    {
      "date": "2026-05-01",
      "o": 5343,
      "h": 5356,
      "l": 5242,
      "c": 5242,
      "v": 1790600,
      "ma5": 5348.4,
      "ma25": 4957.9,
      "ma75": 5024.9,
      "ma200": 4067.0
    },
    {
      "date": "2026-05-07",
      "o": 5742,
      "h": 5942,
      "l": 5651,
      "c": 5763,
      "v": 6871600,
      "ma5": 5440.2,
      "ma25": 5009.8,
      "ma75": 5040.5,
      "ma200": 4082.4
    },
    {
      "date": "2026-05-08",
      "o": 5749,
      "h": 5863,
      "l": 5637,
      "c": 5750,
      "v": 3325300,
      "ma5": 5501.0,
      "ma25": 5069.7,
      "ma75": 5055.1,
      "ma200": 4097.4
    },
    {
      "date": "2026-05-11",
      "o": 5800,
      "h": 5955,
      "l": 5624,
      "c": 5902,
      "v": 3410800,
      "ma5": 5596.8,
      "ma25": 5135.6,
      "ma75": 5070.3,
      "ma200": 4113.3
    },
    {
      "date": "2026-05-12",
      "o": 5945,
      "h": 6073,
      "l": 5797,
      "c": 5841,
      "v": 2567100,
      "ma5": 5699.6,
      "ma25": 5187.2,
      "ma75": 5083.3,
      "ma200": 4128.6
    },
    {
      "date": "2026-05-13",
      "o": 5666,
      "h": 5778,
      "l": 5644,
      "c": 5740,
      "v": 2217500,
      "ma5": 5799.2,
      "ma25": 5239.3,
      "ma75": 5097.3,
      "ma200": 4143.4
    },
    {
      "date": "2026-05-14",
      "o": 5797,
      "h": 5895,
      "l": 5727,
      "c": 5729,
      "v": 3227300,
      "ma5": 5792.4,
      "ma25": 5289.0,
      "ma75": 5110.3,
      "ma200": 4158.2
    },
    {
      "date": "2026-05-15",
      "o": 5819,
      "h": 5892,
      "l": 5445,
      "c": 5533,
      "v": 5374800,
      "ma5": 5749.0,
      "ma25": 5329.2,
      "ma75": 5116.7,
      "ma200": 4171.5
    },
    {
      "date": "2026-05-18",
      "o": 5533,
      "h": 5650,
      "l": 5279,
      "c": 5349,
      "v": 4428300,
      "ma5": 5638.4,
      "ma25": 5360.6,
      "ma75": 5122.0,
      "ma200": 4184.2
    },
    {
      "date": "2026-05-19",
      "o": 5398,
      "h": 5454,
      "l": 5121,
      "c": 5153,
      "v": 3194200,
      "ma5": 5500.8,
      "ma25": 5364.4,
      "ma75": 5124.4,
      "ma200": 4195.8
    },
    {
      "date": "2026-05-20",
      "o": 4980,
      "h": 5055,
      "l": 4870,
      "c": 4935,
      "v": 4155100,
      "ma5": 5339.8,
      "ma25": 5358.6,
      "ma75": 5126.0,
      "ma200": 4205.6
    },
    {
      "date": "2026-05-21",
      "o": 5100,
      "h": 5160,
      "l": 4951,
      "c": 5036,
      "v": 3248800,
      "ma5": 5201.2,
      "ma25": 5355.1,
      "ma75": 5127.4,
      "ma200": 4216.6
    },
    {
      "date": "2026-05-22",
      "o": 5393,
      "h": 5465,
      "l": 5278,
      "c": 5452,
      "v": 4302300,
      "ma5": 5185.0,
      "ma25": 5369.7,
      "ma75": 5136.0,
      "ma200": 4229.6
    },
    {
      "date": "2026-05-25",
      "o": 5697,
      "h": 5830,
      "l": 5651,
      "c": 5693,
      "v": 3711800,
      "ma5": 5253.8,
      "ma25": 5390.6,
      "ma75": 5147.9,
      "ma200": 4243.9
    },
    {
      "date": "2026-05-26",
      "o": 5694,
      "h": 5710,
      "l": 5535,
      "c": 5642,
      "v": 2789100,
      "ma5": 5351.6,
      "ma25": 5416.1,
      "ma75": 5161.1,
      "ma200": 4258.1
    },
    {
      "date": "2026-05-27",
      "o": 5742,
      "h": 5875,
      "l": 5467,
      "c": 5472,
      "v": 3544400,
      "ma5": 5459.0,
      "ma25": 5428.5,
      "ma75": 5170.4,
      "ma200": 4271.6
    },
    {
      "date": "2026-05-28",
      "o": 5572,
      "h": 5625,
      "l": 5361,
      "c": 5499,
      "v": 3110500,
      "ma5": 5551.6,
      "ma25": 5451.2,
      "ma75": 5176.1,
      "ma200": 4285.1
    },
    {
      "date": "2026-05-29",
      "o": 5599,
      "h": 5683,
      "l": 5490,
      "c": 5683,
      "v": 4360300,
      "ma5": 5597.8,
      "ma25": 5473.2,
      "ma75": 5184.5,
      "ma200": 4299.5
    },
    {
      "date": "2026-06-01",
      "o": 5653,
      "h": 5906,
      "l": 5635,
      "c": 5730,
      "v": 3179100,
      "ma5": 5605.2,
      "ma25": 5497.0,
      "ma75": 5194.4,
      "ma200": 4314.2
    },
    {
      "date": "2026-06-02",
      "o": 5698,
      "h": 5700,
      "l": 5247,
      "c": 5357,
      "v": 4060800,
      "ma5": 5548.2,
      "ma25": 5492.4,
      "ma75": 5200.1,
      "ma200": 4327.2
    },
    {
      "date": "2026-06-03",
      "o": 5279,
      "h": 5782,
      "l": 5237,
      "c": 5626,
      "v": 2891700,
      "ma5": 5579.0,
      "ma25": 5505.1,
      "ma75": 5205.8,
      "ma200": 4341.5
    },
    {
      "date": "2026-06-04",
      "o": 5555,
      "h": 5613,
      "l": 5375,
      "c": 5480,
      "v": 2272900,
      "ma5": 5575.2,
      "ma25": 5512.1,
      "ma75": 5207.6,
      "ma200": 4355.1
    },
    {
      "date": "2026-06-05",
      "o": 5471,
      "h": 5553,
      "l": 5342,
      "c": 5535,
      "v": 1687900,
      "ma5": 5545.6,
      "ma25": 5515.7,
      "ma75": 5209.1,
      "ma200": 4368.4
    },
    {
      "date": "2026-06-08",
      "o": 4982,
      "h": 5184,
      "l": 4969,
      "c": 5030,
      "v": 3192900,
      "ma5": 5405.6,
      "ma25": 5500.0,
      "ma75": 5205.4,
      "ma200": 4379.2
    },
    {
      "date": "2026-06-09",
      "o": 5182,
      "h": 5300,
      "l": 5002,
      "c": 5300,
      "v": 2802500,
      "ma5": 5394.2,
      "ma25": 5498.9,
      "ma75": 5200.6,
      "ma200": 4391.0
    },
    {
      "date": "2026-06-10",
      "o": 5283,
      "h": 5388,
      "l": 5171,
      "c": 5265,
      "v": 3427500,
      "ma5": 5322.0,
      "ma25": 5499.8,
      "ma75": 5196.9,
      "ma200": 4402.7
    },
    {
      "date": "2026-06-11",
      "o": 5065,
      "h": 5316,
      "l": 5011,
      "c": 5243,
      "v": 2568200,
      "ma5": 5274.6,
      "ma25": 5479.0,
      "ma75": 5191.3,
      "ma200": 4414.3
    },
    {
      "date": "2026-06-12",
      "o": 5476,
      "h": 5609,
      "l": 5471,
      "c": 5506,
      "v": 2920300,
      "ma5": 5268.8,
      "ma25": 5469.2,
      "ma75": 5191.0,
      "ma200": 4427.3
    },
    {
      "date": "2026-06-15",
      "o": 5765,
      "h": 6204,
      "l": 5719,
      "c": 6204,
      "v": 4425200,
      "ma5": 5503.6,
      "ma25": 5481.3,
      "ma75": 5198.6,
      "ma200": 4442.1
    },
    {
      "date": "2026-06-16",
      "o": 6284,
      "h": 6300,
      "l": 6074,
      "c": 6232,
      "v": 3206000,
      "ma5": 5690.0,
      "ma25": 5497.0,
      "ma75": 5205.9,
      "ma200": 4456.8
    },
    {
      "date": "2026-06-17",
      "o": 6093,
      "h": 6527,
      "l": 6089,
      "c": 6527,
      "v": 3437000,
      "ma5": 5942.4,
      "ma25": 5528.4,
      "ma75": 5218.2,
      "ma200": 4473.3
    },
    {
      "date": "2026-06-18",
      "o": 6578,
      "h": 6774,
      "l": 6538,
      "c": 6694,
      "v": 3696000,
      "ma5": 6232.6,
      "ma25": 5567.0,
      "ma75": 5232.5,
      "ma200": 4491.3
    },
    {
      "date": "2026-06-19",
      "o": 6825,
      "h": 6890,
      "l": 6477,
      "c": 6560,
      "v": 5643000,
      "ma5": 6443.4,
      "ma25": 5608.1,
      "ma75": 5246.1,
      "ma200": 4508.4
    },
    {
      "date": "2026-06-22",
      "o": 6565,
      "h": 6825,
      "l": 6555,
      "c": 6775,
      "v": 1870200,
      "ma5": 6557.6,
      "ma25": 5665.2,
      "ma75": 5262.1,
      "ma200": 4526.5
    },
    {
      "date": "2026-06-23",
      "o": 6711,
      "h": 6814,
      "l": 6342,
      "c": 6356,
      "v": 3439500,
      "ma5": 6582.4,
      "ma25": 5713.3,
      "ma75": 5275.0,
      "ma200": 4542.4
    },
    {
      "date": "2026-06-24",
      "o": 6302,
      "h": 6480,
      "l": 6218,
      "c": 6279,
      "v": 2646800,
      "ma5": 6532.8,
      "ma25": 5767.0,
      "ma75": 5291.5,
      "ma200": 4558.1
    },
    {
      "date": "2026-06-25",
      "o": 6379,
      "h": 6513,
      "l": 6251,
      "c": 6464,
      "v": 4059600,
      "ma5": 6486.8,
      "ma25": 5824.2,
      "ma75": 5307.8,
      "ma200": 4574.9
    },
    {
      "date": "2026-06-26",
      "o": 6410,
      "h": 6523,
      "l": 6101,
      "c": 6248,
      "v": 4188600,
      "ma5": 6424.4,
      "ma25": 5856.0,
      "ma75": 5321.3,
      "ma200": 4590.5
    },
    {
      "date": "2026-06-29",
      "o": 6155,
      "h": 6232,
      "l": 5984,
      "c": 6164,
      "v": 3048200,
      "ma5": 6302.2,
      "ma25": 5874.8,
      "ma75": 5339.1,
      "ma200": 4605.8
    },
    {
      "date": "2026-06-30",
      "o": 6264,
      "h": 6316,
      "l": 6006,
      "c": 6256,
      "v": 3817600,
      "ma5": 6282.2,
      "ma25": 5899.4,
      "ma75": 5354.5,
      "ma200": 4622.0
    },
    {
      "date": "2026-07-01",
      "o": 6266,
      "h": 6444,
      "l": 6226,
      "c": 6300,
      "v": 3763100,
      "ma5": 6286.4,
      "ma25": 5932.5,
      "ma75": 5368.9,
      "ma200": 4638.2
    }
  ]
}