{
  "version": 2,
  "code": "90200",
  "name": "東日本旅客鉄道",
  "market": "東証P",
  "sector": "陸運業",
  "header": {
    "price": 3386,
    "change": 43,
    "changePct": 1.3,
    "isStopHigh": false,
    "turnoverPct": 0.2,
    "marketCap": 3841119709200,
    "appearCount": 0,
    "stopHighCount": 0
  },
  "rows": [
    {
      "date": "2026-04-14",
      "o": 3580,
      "h": 3584,
      "l": 3505,
      "c": 3514,
      "v": 2934700,
      "ma5": 3572.4,
      "ma25": 3648.0,
      "ma75": 3838.8,
      "ma200": 3681.8
    },
    {
      "date": "2026-04-15",
      "o": 3533,
      "h": 3584,
      "l": 3525,
      "c": 3582,
      "v": 2776800,
      "ma5": 3567.2,
      "ma25": 3641.1,
      "ma75": 3833.0,
      "ma200": 3684.1
    },
    {
      "date": "2026-04-16",
      "o": 3559,
      "h": 3590,
      "l": 3525,
      "c": 3525,
      "v": 2488400,
      "ma5": 3556.4,
      "ma25": 3629.4,
      "ma75": 3825.6,
      "ma200": 3686.5
    },
    {
      "date": "2026-04-17",
      "o": 3520,
      "h": 3530,
      "l": 3475,
      "c": 3478,
      "v": 2905800,
      "ma5": 3540.2,
      "ma25": 3618.0,
      "ma75": 3816.9,
      "ma200": 3688.6
    },
    {
      "date": "2026-04-20",
      "o": 3500,
      "h": 3535,
      "l": 3491,
      "c": 3517,
      "v": 2200200,
      "ma5": 3523.2,
      "ma25": 3609.9,
      "ma75": 3808.5,
      "ma200": 3690.8
    },
    {
      "date": "2026-04-21",
      "o": 3517,
      "h": 3544,
      "l": 3487,
      "c": 3544,
      "v": 3282400,
      "ma5": 3529.2,
      "ma25": 3602.8,
      "ma75": 3800.3,
      "ma200": 3693.3
    },
    {
      "date": "2026-04-22",
      "o": 3528,
      "h": 3545,
      "l": 3511,
      "c": 3522,
      "v": 2783900,
      "ma5": 3517.2,
      "ma25": 3593.4,
      "ma75": 3791.9,
      "ma200": 3695.6
    },
    {
      "date": "2026-04-23",
      "o": 3500,
      "h": 3512,
      "l": 3476,
      "c": 3501,
      "v": 2867300,
      "ma5": 3512.4,
      "ma25": 3585.4,
      "ma75": 3783.4,
      "ma200": 3697.7
    },
    {
      "date": "2026-04-24",
      "o": 3474,
      "h": 3485,
      "l": 3418,
      "c": 3461,
      "v": 2823300,
      "ma5": 3509.0,
      "ma25": 3579.4,
      "ma75": 3774.2,
      "ma200": 3699.4
    },
    {
      "date": "2026-04-27",
      "o": 3402,
      "h": 3461,
      "l": 3391,
      "c": 3427,
      "v": 2458400,
      "ma5": 3491.0,
      "ma25": 3574.2,
      "ma75": 3764.1,
      "ma200": 3700.9
    },
    {
      "date": "2026-04-28",
      "o": 3460,
      "h": 3464,
      "l": 3415,
      "c": 3451,
      "v": 2637900,
      "ma5": 3472.4,
      "ma25": 3568.7,
      "ma75": 3755.1,
      "ma200": 3702.2
    },
    {
      "date": "2026-04-30",
      "o": 3381,
      "h": 3451,
      "l": 3277,
      "c": 3388,
      "v": 7890400,
      "ma5": 3445.6,
      "ma25": 3558.8,
      "ma75": 3745.2,
      "ma200": 3703.3
    },
    {
      "date": "2026-05-01",
      "o": 3668,
      "h": 3785,
      "l": 3602,
      "c": 3700,
      "v": 8824700,
      "ma5": 3485.4,
      "ma25": 3560.9,
      "ma75": 3739.2,
      "ma200": 3706.1
    },
    {
      "date": "2026-05-07",
      "o": 3573,
      "h": 3709,
      "l": 3567,
      "c": 3610,
      "v": 6540600,
      "ma5": 3515.2,
      "ma25": 3558.5,
      "ma75": 3731.5,
      "ma200": 3708.3
    },
    {
      "date": "2026-05-08",
      "o": 3648,
      "h": 3666,
      "l": 3600,
      "c": 3645,
      "v": 6176200,
      "ma5": 3558.8,
      "ma25": 3559.5,
      "ma75": 3724.9,
      "ma200": 3710.7
    },
    {
      "date": "2026-05-11",
      "o": 3626,
      "h": 3690,
      "l": 3611,
      "c": 3639,
      "v": 3352900,
      "ma5": 3596.4,
      "ma25": 3560.0,
      "ma75": 3719.1,
      "ma200": 3712.9
    },
    {
      "date": "2026-05-12",
      "o": 3641,
      "h": 3698,
      "l": 3588,
      "c": 3693,
      "v": 3630000,
      "ma5": 3657.4,
      "ma25": 3560.4,
      "ma75": 3715.6,
      "ma200": 3715.2
    },
    {
      "date": "2026-05-13",
      "o": 3752,
      "h": 3802,
      "l": 3744,
      "c": 3764,
      "v": 3644200,
      "ma5": 3670.2,
      "ma25": 3564.0,
      "ma75": 3713.4,
      "ma200": 3717.9
    },
    {
      "date": "2026-05-14",
      "o": 3716,
      "h": 3724,
      "l": 3661,
      "c": 3680,
      "v": 2981900,
      "ma5": 3684.2,
      "ma25": 3565.6,
      "ma75": 3709.0,
      "ma200": 3720.3
    },
    {
      "date": "2026-05-15",
      "o": 3675,
      "h": 3773,
      "l": 3657,
      "c": 3766,
      "v": 5927800,
      "ma5": 3708.4,
      "ma25": 3573.2,
      "ma75": 3706.0,
      "ma200": 3723.4
    },
    {
      "date": "2026-05-18",
      "o": 3792,
      "h": 3796,
      "l": 3682,
      "c": 3682,
      "v": 2981900,
      "ma5": 3717.0,
      "ma25": 3577.5,
      "ma75": 3702.2,
      "ma200": 3726.1
    },
    {
      "date": "2026-05-19",
      "o": 3746,
      "h": 3819,
      "l": 3730,
      "c": 3788,
      "v": 2606100,
      "ma5": 3736.0,
      "ma25": 3584.7,
      "ma75": 3699.9,
      "ma200": 3729.2
    },
    {
      "date": "2026-05-20",
      "o": 3840,
      "h": 3844,
      "l": 3729,
      "c": 3775,
      "v": 2407700,
      "ma5": 3738.2,
      "ma25": 3592.5,
      "ma75": 3697.3,
      "ma200": 3732.3
    },
    {
      "date": "2026-05-21",
      "o": 3800,
      "h": 3844,
      "l": 3692,
      "c": 3692,
      "v": 2559800,
      "ma5": 3740.6,
      "ma25": 3597.8,
      "ma75": 3694.2,
      "ma200": 3735.0
    },
    {
      "date": "2026-05-22",
      "o": 3645,
      "h": 3670,
      "l": 3603,
      "c": 3606,
      "v": 3017100,
      "ma5": 3708.6,
      "ma25": 3598.0,
      "ma75": 3691.6,
      "ma200": 3737.1
    },
    {
      "date": "2026-05-25",
      "o": 3591,
      "h": 3597,
      "l": 3518,
      "c": 3570,
      "v": 2398500,
      "ma5": 3686.2,
      "ma25": 3600.2,
      "ma75": 3688.0,
      "ma200": 3739.0
    },
    {
      "date": "2026-05-26",
      "o": 3564,
      "h": 3570,
      "l": 3524,
      "c": 3551,
      "v": 3008700,
      "ma5": 3638.8,
      "ma25": 3599.0,
      "ma75": 3683.4,
      "ma200": 3740.8
    },
    {
      "date": "2026-05-27",
      "o": 3532,
      "h": 3535,
      "l": 3458,
      "c": 3528,
      "v": 3600500,
      "ma5": 3589.4,
      "ma25": 3599.1,
      "ma75": 3679.9,
      "ma200": 3742.5
    },
    {
      "date": "2026-05-28",
      "o": 3516,
      "h": 3531,
      "l": 3444,
      "c": 3444,
      "v": 4076100,
      "ma5": 3539.8,
      "ma25": 3597.8,
      "ma75": 3675.9,
      "ma200": 3744.0
    },
    {
      "date": "2026-05-29",
      "o": 3438,
      "h": 3500,
      "l": 3412,
      "c": 3412,
      "v": 6800400,
      "ma5": 3501.0,
      "ma25": 3593.6,
      "ma75": 3671.2,
      "ma200": 3745.0
    },
    {
      "date": "2026-06-01",
      "o": 3441,
      "h": 3466,
      "l": 3325,
      "c": 3354,
      "v": 3646500,
      "ma5": 3457.8,
      "ma25": 3586.0,
      "ma75": 3664.5,
      "ma200": 3745.7
    },
    {
      "date": "2026-06-02",
      "o": 3335,
      "h": 3365,
      "l": 3292,
      "c": 3345,
      "v": 2977100,
      "ma5": 3416.6,
      "ma25": 3578.9,
      "ma75": 3656.0,
      "ma200": 3745.7
    },
    {
      "date": "2026-06-03",
      "o": 3295,
      "h": 3333,
      "l": 3262,
      "c": 3313,
      "v": 4419400,
      "ma5": 3373.6,
      "ma25": 3571.4,
      "ma75": 3647.8,
      "ma200": 3745.7
    },
    {
      "date": "2026-06-04",
      "o": 3317,
      "h": 3318,
      "l": 3243,
      "c": 3280,
      "v": 3704900,
      "ma5": 3340.8,
      "ma25": 3564.1,
      "ma75": 3639.7,
      "ma200": 3745.3
    },
    {
      "date": "2026-06-05",
      "o": 3292,
      "h": 3399,
      "l": 3279,
      "c": 3366,
      "v": 5454000,
      "ma5": 3331.6,
      "ma25": 3561.7,
      "ma75": 3634.3,
      "ma200": 3744.8
    },
    {
      "date": "2026-06-08",
      "o": 3400,
      "h": 3418,
      "l": 3345,
      "c": 3380,
      "v": 3307600,
      "ma5": 3336.8,
      "ma25": 3558.8,
      "ma75": 3628.6,
      "ma200": 3744.4
    },
    {
      "date": "2026-06-09",
      "o": 3444,
      "h": 3459,
      "l": 3377,
      "c": 3383,
      "v": 3568500,
      "ma5": 3344.4,
      "ma25": 3558.6,
      "ma75": 3623.2,
      "ma200": 3743.7
    },
    {
      "date": "2026-06-10",
      "o": 3413,
      "h": 3463,
      "l": 3373,
      "c": 3460,
      "v": 3237900,
      "ma5": 3373.8,
      "ma25": 3549.0,
      "ma75": 3619.2,
      "ma200": 3743.3
    },
    {
      "date": "2026-06-11",
      "o": 3500,
      "h": 3513,
      "l": 3414,
      "c": 3460,
      "v": 5537400,
      "ma5": 3409.8,
      "ma25": 3543.0,
      "ma75": 3614.1,
      "ma200": 3743.0
    },
    {
      "date": "2026-06-12",
      "o": 3450,
      "h": 3467,
      "l": 3389,
      "c": 3404,
      "v": 3564300,
      "ma5": 3417.4,
      "ma25": 3533.4,
      "ma75": 3608.4,
      "ma200": 3742.5
    },
    {
      "date": "2026-06-15",
      "o": 3410,
      "h": 3443,
      "l": 3362,
      "c": 3377,
      "v": 2912600,
      "ma5": 3416.8,
      "ma25": 3522.9,
      "ma75": 3602.6,
      "ma200": 3741.6
    },
    {
      "date": "2026-06-16",
      "o": 3385,
      "h": 3400,
      "l": 3356,
      "c": 3398,
      "v": 2510800,
      "ma5": 3419.8,
      "ma25": 3511.1,
      "ma75": 3596.9,
      "ma200": 3740.6
    },
    {
      "date": "2026-06-17",
      "o": 3445,
      "h": 3455,
      "l": 3336,
      "c": 3345,
      "v": 2698700,
      "ma5": 3396.8,
      "ma25": 3494.4,
      "ma75": 3590.5,
      "ma200": 3739.3
    },
    {
      "date": "2026-06-18",
      "o": 3363,
      "h": 3400,
      "l": 3313,
      "c": 3393,
      "v": 3116600,
      "ma5": 3383.4,
      "ma25": 3482.9,
      "ma75": 3584.5,
      "ma200": 3738.0
    },
    {
      "date": "2026-06-19",
      "o": 3368,
      "h": 3415,
      "l": 3320,
      "c": 3415,
      "v": 6408600,
      "ma5": 3385.6,
      "ma25": 3468.8,
      "ma75": 3578.6,
      "ma200": 3737.1
    },
    {
      "date": "2026-06-22",
      "o": 3347,
      "h": 3382,
      "l": 3314,
      "c": 3324,
      "v": 2438900,
      "ma5": 3375.0,
      "ma25": 3454.5,
      "ma75": 3571.2,
      "ma200": 3735.4
    },
    {
      "date": "2026-06-23",
      "o": 3322,
      "h": 3373,
      "l": 3306,
      "c": 3351,
      "v": 2944600,
      "ma5": 3365.6,
      "ma25": 3437.0,
      "ma75": 3565.6,
      "ma200": 3734.2
    },
    {
      "date": "2026-06-24",
      "o": 3395,
      "h": 3407,
      "l": 3352,
      "c": 3363,
      "v": 2475400,
      "ma5": 3369.2,
      "ma25": 3420.6,
      "ma75": 3561.1,
      "ma200": 3733.4
    },
    {
      "date": "2026-06-25",
      "o": 3371,
      "h": 3393,
      "l": 3332,
      "c": 3343,
      "v": 1989500,
      "ma5": 3359.2,
      "ma25": 3406.6,
      "ma75": 3555.9,
      "ma200": 3732.3
    },
    {
      "date": "2026-06-26",
      "o": 3381,
      "h": 3388,
      "l": 3338,
      "c": 3386,
      "v": 1957000,
      "ma5": 3353.4,
      "ma25": 3397.8,
      "ma75": 3551.6,
      "ma200": 3731.0
    }
  ]
}