{
  "version": 2,
  "code": "92350",
  "name": "売れるネット広告社グループ",
  "market": "東証G",
  "sector": "サービス業",
  "header": {
    "price": 489,
    "change": -2,
    "changePct": -0.4,
    "isStopHigh": false,
    "turnoverPct": 0.5,
    "marketCap": 3768131799,
    "appearCount": 11,
    "stopHighCount": 2
  },
  "rows": [
    {
      "date": "2026-04-13",
      "o": 562,
      "h": 569,
      "l": 553,
      "c": 560,
      "v": 93600,
      "ma5": 576.4,
      "ma25": 597.9,
      "ma75": 625.2,
      "ma200": 1014.2
    },
    {
      "date": "2026-04-14",
      "o": 570,
      "h": 579,
      "l": 567,
      "c": 570,
      "v": 121600,
      "ma5": 577.0,
      "ma25": 598.1,
      "ma75": 624.3,
      "ma200": 1008.5
    },
    {
      "date": "2026-04-15",
      "o": 570,
      "h": 619,
      "l": 557,
      "c": 575,
      "v": 318500,
      "ma5": 571.6,
      "ma25": 597.3,
      "ma75": 624.0,
      "ma200": 1002.9,
      "marks": [
        "appear"
      ]
    },
    {
      "date": "2026-04-16",
      "o": 575,
      "h": 589,
      "l": 575,
      "c": 581,
      "v": 114500,
      "ma5": 571.6,
      "ma25": 596.9,
      "ma75": 622.4,
      "ma200": 997.6
    },
    {
      "date": "2026-04-17",
      "o": 580,
      "h": 592,
      "l": 576,
      "c": 589,
      "v": 96700,
      "ma5": 575.0,
      "ma25": 596.9,
      "ma75": 620.5,
      "ma200": 992.7
    },
    {
      "date": "2026-04-20",
      "o": 594,
      "h": 610,
      "l": 587,
      "c": 604,
      "v": 88600,
      "ma5": 583.8,
      "ma25": 597.8,
      "ma75": 619.5,
      "ma200": 987.1
    },
    {
      "date": "2026-04-21",
      "o": 606,
      "h": 606,
      "l": 583,
      "c": 584,
      "v": 97500,
      "ma5": 586.6,
      "ma25": 599.3,
      "ma75": 617.8,
      "ma200": 981.1
    },
    {
      "date": "2026-04-22",
      "o": 578,
      "h": 582,
      "l": 560,
      "c": 569,
      "v": 89100,
      "ma5": 585.4,
      "ma25": 600.0,
      "ma75": 616.2,
      "ma200": 975.4
    },
    {
      "date": "2026-04-23",
      "o": 571,
      "h": 573,
      "l": 562,
      "c": 565,
      "v": 52400,
      "ma5": 582.2,
      "ma25": 600.3,
      "ma75": 614.9,
      "ma200": 970.0
    },
    {
      "date": "2026-04-24",
      "o": 566,
      "h": 571,
      "l": 562,
      "c": 566,
      "v": 39300,
      "ma5": 577.6,
      "ma25": 601.8,
      "ma75": 613.9,
      "ma200": 964.6
    },
    {
      "date": "2026-04-27",
      "o": 561,
      "h": 562,
      "l": 544,
      "c": 556,
      "v": 80000,
      "ma5": 568.0,
      "ma25": 603.7,
      "ma75": 612.5,
      "ma200": 959.1
    },
    {
      "date": "2026-04-28",
      "o": 552,
      "h": 557,
      "l": 545,
      "c": 554,
      "v": 37400,
      "ma5": 562.0,
      "ma25": 601.5,
      "ma75": 611.2,
      "ma200": 954.6
    },
    {
      "date": "2026-04-30",
      "o": 554,
      "h": 554,
      "l": 541,
      "c": 554,
      "v": 60400,
      "ma5": 559.0,
      "ma25": 595.4,
      "ma75": 609.8,
      "ma200": 950.5
    },
    {
      "date": "2026-05-01",
      "o": 551,
      "h": 556,
      "l": 547,
      "c": 552,
      "v": 19100,
      "ma5": 556.4,
      "ma25": 587.4,
      "ma75": 608.4,
      "ma200": 946.6
    },
    {
      "date": "2026-05-07",
      "o": 601,
      "h": 652,
      "l": 597,
      "c": 652,
      "v": 954700,
      "ma5": 573.6,
      "ma25": 581.9,
      "ma75": 608.2,
      "ma200": 941.8,
      "marks": [
        "shc",
        "turn5",
        "appear"
      ]
    },
    {
      "date": "2026-05-08",
      "o": 752,
      "h": 752,
      "l": 752,
      "c": 752,
      "v": 26600,
      "ma5": 612.8,
      "ma25": 585.1,
      "ma75": 609.4,
      "ma200": 937.4,
      "marks": [
        "shc"
      ]
    },
    {
      "date": "2026-05-11",
      "o": 805,
      "h": 893,
      "l": 728,
      "c": 797,
      "v": 3983000,
      "ma5": 661.4,
      "ma25": 592.2,
      "ma75": 610.9,
      "ma200": 932.7,
      "marks": [
        "turn5",
        "appear"
      ]
    },
    {
      "date": "2026-05-12",
      "o": 767,
      "h": 789,
      "l": 670,
      "c": 696,
      "v": 1087500,
      "ma5": 689.8,
      "ma25": 594.9,
      "ma75": 611.4,
      "ma200": 927.9,
      "marks": [
        "turn5",
        "appear"
      ]
    },
    {
      "date": "2026-05-13",
      "o": 680,
      "h": 694,
      "l": 661,
      "c": 667,
      "v": 408900,
      "ma5": 712.8,
      "ma25": 599.0,
      "ma75": 610.8,
      "ma200": 923.4,
      "marks": [
        "turn5",
        "appear"
      ]
    },
    {
      "date": "2026-05-14",
      "o": 697,
      "h": 719,
      "l": 625,
      "c": 630,
      "v": 396800,
      "ma5": 708.4,
      "ma25": 602.3,
      "ma75": 609.8,
      "ma200": 918.9,
      "marks": [
        "turn5",
        "appear"
      ]
    },
    {
      "date": "2026-05-15",
      "o": 640,
      "h": 658,
      "l": 626,
      "c": 633,
      "v": 239600,
      "ma5": 684.6,
      "ma25": 605.1,
      "ma75": 609.5,
      "ma200": 914.7
    },
    {
      "date": "2026-05-18",
      "o": 636,
      "h": 636,
      "l": 607,
      "c": 630,
      "v": 159500,
      "ma5": 651.2,
      "ma25": 607.6,
      "ma75": 609.0,
      "ma200": 909.9
    },
    {
      "date": "2026-05-19",
      "o": 621,
      "h": 637,
      "l": 614,
      "c": 624,
      "v": 98200,
      "ma5": 636.8,
      "ma25": 608.5,
      "ma75": 608.3,
      "ma200": 905.1
    },
    {
      "date": "2026-05-20",
      "o": 622,
      "h": 628,
      "l": 601,
      "c": 607,
      "v": 125800,
      "ma5": 624.8,
      "ma25": 609.6,
      "ma75": 607.6,
      "ma200": 900.3
    },
    {
      "date": "2026-05-21",
      "o": 609,
      "h": 614,
      "l": 585,
      "c": 594,
      "v": 234100,
      "ma5": 617.6,
      "ma25": 610.4,
      "ma75": 605.4,
      "ma200": 895.6,
      "marks": [
        "appear"
      ]
    },
    {
      "date": "2026-05-22",
      "o": 596,
      "h": 605,
      "l": 580,
      "c": 597,
      "v": 109400,
      "ma5": 610.4,
      "ma25": 611.9,
      "ma75": 604.2,
      "ma200": 891.0
    },
    {
      "date": "2026-05-25",
      "o": 637,
      "h": 655,
      "l": 582,
      "c": 585,
      "v": 446400,
      "ma5": 601.4,
      "ma25": 612.5,
      "ma75": 603.5,
      "ma200": 886.4,
      "marks": [
        "turn5",
        "appear"
      ]
    },
    {
      "date": "2026-05-26",
      "o": 582,
      "h": 633,
      "l": 560,
      "c": 563,
      "v": 538500,
      "ma5": 589.2,
      "ma25": 612.0,
      "ma75": 602.8,
      "ma200": 881.6,
      "marks": [
        "turn5",
        "appear"
      ]
    },
    {
      "date": "2026-05-27",
      "o": 565,
      "h": 600,
      "l": 555,
      "c": 588,
      "v": 467700,
      "ma5": 585.4,
      "ma25": 612.3,
      "ma75": 602.4,
      "ma200": 877.0,
      "marks": [
        "turn5",
        "appear"
      ]
    },
    {
      "date": "2026-05-28",
      "o": 581,
      "h": 606,
      "l": 547,
      "c": 566,
      "v": 349200,
      "ma5": 579.8,
      "ma25": 611.4,
      "ma75": 601.6,
      "ma200": 872.4,
      "marks": [
        "appear"
      ]
    },
    {
      "date": "2026-05-29",
      "o": 565,
      "h": 588,
      "l": 555,
      "c": 559,
      "v": 207200,
      "ma5": 572.2,
      "ma25": 609.6,
      "ma75": 600.9,
      "ma200": 868.2
    },
    {
      "date": "2026-06-01",
      "o": 566,
      "h": 566,
      "l": 530,
      "c": 546,
      "v": 154500,
      "ma5": 564.4,
      "ma25": 608.1,
      "ma75": 599.8,
      "ma200": 863.9
    },
    {
      "date": "2026-06-02",
      "o": 536,
      "h": 543,
      "l": 525,
      "c": 533,
      "v": 80700,
      "ma5": 558.4,
      "ma25": 606.6,
      "ma75": 598.7,
      "ma200": 859.7
    },
    {
      "date": "2026-06-03",
      "o": 535,
      "h": 540,
      "l": 515,
      "c": 532,
      "v": 102200,
      "ma5": 547.2,
      "ma25": 605.3,
      "ma75": 597.5,
      "ma200": 855.6
    },
    {
      "date": "2026-06-04",
      "o": 530,
      "h": 530,
      "l": 520,
      "c": 521,
      "v": 69500,
      "ma5": 538.2,
      "ma25": 603.5,
      "ma75": 595.9,
      "ma200": 851.4
    },
    {
      "date": "2026-06-05",
      "o": 522,
      "h": 541,
      "l": 522,
      "c": 536,
      "v": 67100,
      "ma5": 533.6,
      "ma25": 602.7,
      "ma75": 594.9,
      "ma200": 847.3
    },
    {
      "date": "2026-06-08",
      "o": 526,
      "h": 528,
      "l": 513,
      "c": 517,
      "v": 81200,
      "ma5": 527.8,
      "ma25": 601.2,
      "ma75": 593.8,
      "ma200": 843.0
    },
    {
      "date": "2026-06-09",
      "o": 525,
      "h": 544,
      "l": 522,
      "c": 534,
      "v": 134500,
      "ma5": 528.0,
      "ma25": 600.4,
      "ma75": 592.6,
      "ma200": 838.8
    },
    {
      "date": "2026-06-10",
      "o": 521,
      "h": 524,
      "l": 513,
      "c": 521,
      "v": 77800,
      "ma5": 525.8,
      "ma25": 599.2,
      "ma75": 591.3,
      "ma200": 834.6
    },
    {
      "date": "2026-06-11",
      "o": 514,
      "h": 521,
      "l": 505,
      "c": 514,
      "v": 76200,
      "ma5": 524.4,
      "ma25": 593.7,
      "ma75": 590.0,
      "ma200": 830.2
    },
    {
      "date": "2026-06-12",
      "o": 524,
      "h": 536,
      "l": 516,
      "c": 536,
      "v": 61500,
      "ma5": 524.4,
      "ma25": 585.0,
      "ma75": 588.9,
      "ma200": 825.9
    },
    {
      "date": "2026-06-15",
      "o": 510,
      "h": 522,
      "l": 496,
      "c": 500,
      "v": 168700,
      "ma5": 521.0,
      "ma25": 573.2,
      "ma75": 587.7,
      "ma200": 821.2
    },
    {
      "date": "2026-06-16",
      "o": 500,
      "h": 515,
      "l": 486,
      "c": 515,
      "v": 112300,
      "ma5": 517.2,
      "ma25": 565.9,
      "ma75": 587.0,
      "ma200": 816.5
    },
    {
      "date": "2026-06-17",
      "o": 517,
      "h": 523,
      "l": 498,
      "c": 513,
      "v": 81800,
      "ma5": 515.6,
      "ma25": 559.8,
      "ma75": 586.1,
      "ma200": 811.7
    },
    {
      "date": "2026-06-18",
      "o": 516,
      "h": 518,
      "l": 500,
      "c": 506,
      "v": 56500,
      "ma5": 514.0,
      "ma25": 554.8,
      "ma75": 584.8,
      "ma200": 807.0
    },
    {
      "date": "2026-06-19",
      "o": 512,
      "h": 512,
      "l": 496,
      "c": 497,
      "v": 42900,
      "ma5": 506.2,
      "ma25": 549.4,
      "ma75": 583.3,
      "ma200": 802.0
    },
    {
      "date": "2026-06-22",
      "o": 499,
      "h": 515,
      "l": 496,
      "c": 504,
      "v": 38200,
      "ma5": 507.0,
      "ma25": 544.3,
      "ma75": 582.3,
      "ma200": 796.9
    },
    {
      "date": "2026-06-23",
      "o": 501,
      "h": 501,
      "l": 491,
      "c": 491,
      "v": 36100,
      "ma5": 502.2,
      "ma25": 539.0,
      "ma75": 581.4,
      "ma200": 791.8
    },
    {
      "date": "2026-06-24",
      "o": 491,
      "h": 499,
      "l": 491,
      "c": 491,
      "v": 25200,
      "ma5": 497.8,
      "ma25": 534.4,
      "ma75": 580.8,
      "ma200": 787.0
    },
    {
      "date": "2026-06-25",
      "o": 493,
      "h": 503,
      "l": 488,
      "c": 489,
      "v": 37200,
      "ma5": 494.4,
      "ma25": 530.2,
      "ma75": 579.8,
      "ma200": 782.2
    }
  ]
}