{
  "version": 2,
  "code": "93370",
  "name": "トリドリ",
  "market": "東証G",
  "sector": "サービス業",
  "header": {
    "price": 1497,
    "change": 2,
    "changePct": 0.1,
    "isStopHigh": false,
    "turnoverPct": 0.3,
    "marketCap": 4944321540,
    "appearCount": 0,
    "stopHighCount": 1
  },
  "rows": [
    {
      "date": "2026-04-16",
      "o": 1953,
      "h": 1996,
      "l": 1867,
      "c": 1870,
      "v": 22700,
      "ma5": 1887.6,
      "ma25": 1699.1,
      "ma75": 2396.7,
      "ma200": 2549.8
    },
    {
      "date": "2026-04-17",
      "o": 1877,
      "h": 1910,
      "l": 1867,
      "c": 1897,
      "v": 14700,
      "ma5": 1900.8,
      "ma25": 1708.5,
      "ma75": 2378.3,
      "ma200": 2549.3
    },
    {
      "date": "2026-04-20",
      "o": 1919,
      "h": 1920,
      "l": 1881,
      "c": 1881,
      "v": 11100,
      "ma5": 1905.0,
      "ma25": 1717.2,
      "ma75": 2360.8,
      "ma200": 2548.3
    },
    {
      "date": "2026-04-21",
      "o": 1889,
      "h": 1919,
      "l": 1866,
      "c": 1880,
      "v": 18800,
      "ma5": 1896.6,
      "ma25": 1726.0,
      "ma75": 2343.6,
      "ma200": 2547.4
    },
    {
      "date": "2026-04-22",
      "o": 1866,
      "h": 1885,
      "l": 1854,
      "c": 1854,
      "v": 13700,
      "ma5": 1876.4,
      "ma25": 1733.8,
      "ma75": 2327.6,
      "ma200": 2546.3
    },
    {
      "date": "2026-04-23",
      "o": 1854,
      "h": 1854,
      "l": 1774,
      "c": 1791,
      "v": 27900,
      "ma5": 1860.6,
      "ma25": 1738.2,
      "ma75": 2310.2,
      "ma200": 2544.7
    },
    {
      "date": "2026-04-24",
      "o": 1783,
      "h": 1783,
      "l": 1700,
      "c": 1703,
      "v": 18000,
      "ma5": 1821.8,
      "ma25": 1742.6,
      "ma75": 2290.9,
      "ma200": 2542.3
    },
    {
      "date": "2026-04-27",
      "o": 1703,
      "h": 1710,
      "l": 1653,
      "c": 1653,
      "v": 17700,
      "ma5": 1776.2,
      "ma25": 1747.8,
      "ma75": 2269.1,
      "ma200": 2539.9
    },
    {
      "date": "2026-04-28",
      "o": 1653,
      "h": 1660,
      "l": 1630,
      "c": 1638,
      "v": 15800,
      "ma5": 1727.8,
      "ma25": 1749.1,
      "ma75": 2248.0,
      "ma200": 2537.6
    },
    {
      "date": "2026-04-30",
      "o": 1632,
      "h": 1635,
      "l": 1601,
      "c": 1616,
      "v": 23900,
      "ma5": 1680.2,
      "ma25": 1747.7,
      "ma75": 2227.0,
      "ma200": 2535.5
    },
    {
      "date": "2026-05-01",
      "o": 1605,
      "h": 1652,
      "l": 1605,
      "c": 1605,
      "v": 21400,
      "ma5": 1643.0,
      "ma25": 1748.8,
      "ma75": 2206.9,
      "ma200": 2533.5
    },
    {
      "date": "2026-05-07",
      "o": 1670,
      "h": 1670,
      "l": 1590,
      "c": 1607,
      "v": 19500,
      "ma5": 1623.8,
      "ma25": 1749.1,
      "ma75": 2188.2,
      "ma200": 2531.3
    },
    {
      "date": "2026-05-08",
      "o": 1567,
      "h": 1635,
      "l": 1567,
      "c": 1612,
      "v": 31400,
      "ma5": 1615.6,
      "ma25": 1752.4,
      "ma75": 2169.2,
      "ma200": 2528.8
    },
    {
      "date": "2026-05-11",
      "o": 1620,
      "h": 1662,
      "l": 1589,
      "c": 1653,
      "v": 17200,
      "ma5": 1618.6,
      "ma25": 1757.1,
      "ma75": 2145.3,
      "ma200": 2526.3
    },
    {
      "date": "2026-05-12",
      "o": 1641,
      "h": 1641,
      "l": 1592,
      "c": 1595,
      "v": 24900,
      "ma5": 1614.4,
      "ma25": 1756.5,
      "ma75": 2120.7,
      "ma200": 2523.2
    },
    {
      "date": "2026-05-13",
      "o": 1581,
      "h": 1617,
      "l": 1567,
      "c": 1617,
      "v": 13200,
      "ma5": 1616.8,
      "ma25": 1755.7,
      "ma75": 2095.9,
      "ma200": 2520.2
    },
    {
      "date": "2026-05-14",
      "o": 1626,
      "h": 1626,
      "l": 1480,
      "c": 1493,
      "v": 87400,
      "ma5": 1594.0,
      "ma25": 1750.5,
      "ma75": 2069.8,
      "ma200": 2516.5
    },
    {
      "date": "2026-05-15",
      "o": 1650,
      "h": 1793,
      "l": 1618,
      "c": 1730,
      "v": 136500,
      "ma5": 1617.6,
      "ma25": 1749.8,
      "ma75": 2046.8,
      "ma200": 2514.5,
      "marks": [
        "sht"
      ]
    },
    {
      "date": "2026-05-18",
      "o": 1816,
      "h": 1980,
      "l": 1759,
      "c": 1935,
      "v": 84600,
      "ma5": 1674.0,
      "ma25": 1755.8,
      "ma75": 2026.6,
      "ma200": 2513.8
    },
    {
      "date": "2026-05-19",
      "o": 1956,
      "h": 2045,
      "l": 1905,
      "c": 1953,
      "v": 51300,
      "ma5": 1745.6,
      "ma25": 1758.6,
      "ma75": 2005.4,
      "ma200": 2512.9
    },
    {
      "date": "2026-05-20",
      "o": 1973,
      "h": 1973,
      "l": 1814,
      "c": 1814,
      "v": 54700,
      "ma5": 1785.0,
      "ma25": 1758.6,
      "ma75": 1982.7,
      "ma200": 2511.6
    },
    {
      "date": "2026-05-21",
      "o": 1815,
      "h": 1818,
      "l": 1736,
      "c": 1736,
      "v": 25600,
      "ma5": 1833.6,
      "ma25": 1754.8,
      "ma75": 1960.7,
      "ma200": 2509.5
    },
    {
      "date": "2026-05-22",
      "o": 1745,
      "h": 1745,
      "l": 1672,
      "c": 1715,
      "v": 26700,
      "ma5": 1830.6,
      "ma25": 1749.0,
      "ma75": 1938.6,
      "ma200": 2506.8
    },
    {
      "date": "2026-05-25",
      "o": 1730,
      "h": 1730,
      "l": 1620,
      "c": 1652,
      "v": 29000,
      "ma5": 1774.0,
      "ma25": 1738.2,
      "ma75": 1914.4,
      "ma200": 2504.0
    },
    {
      "date": "2026-05-26",
      "o": 1631,
      "h": 1637,
      "l": 1577,
      "c": 1600,
      "v": 38400,
      "ma5": 1703.4,
      "ma25": 1724.0,
      "ma75": 1889.7,
      "ma200": 2501.0
    },
    {
      "date": "2026-05-27",
      "o": 1601,
      "h": 1624,
      "l": 1585,
      "c": 1601,
      "v": 22900,
      "ma5": 1660.8,
      "ma25": 1713.2,
      "ma75": 1866.2,
      "ma200": 2498.0
    },
    {
      "date": "2026-05-28",
      "o": 1602,
      "h": 1619,
      "l": 1569,
      "c": 1572,
      "v": 31300,
      "ma5": 1628.0,
      "ma25": 1700.2,
      "ma75": 1842.9,
      "ma200": 2494.8
    },
    {
      "date": "2026-05-29",
      "o": 1612,
      "h": 1645,
      "l": 1586,
      "c": 1586,
      "v": 27900,
      "ma5": 1602.2,
      "ma25": 1688.4,
      "ma75": 1822.3,
      "ma200": 2491.8
    },
    {
      "date": "2026-06-01",
      "o": 1608,
      "h": 1658,
      "l": 1588,
      "c": 1645,
      "v": 28600,
      "ma5": 1600.8,
      "ma25": 1679.0,
      "ma75": 1802.2,
      "ma200": 2488.8
    },
    {
      "date": "2026-06-02",
      "o": 1679,
      "h": 1680,
      "l": 1564,
      "c": 1643,
      "v": 88900,
      "ma5": 1609.4,
      "ma25": 1670.6,
      "ma75": 1782.4,
      "ma200": 2485.9
    },
    {
      "date": "2026-06-03",
      "o": 1634,
      "h": 1683,
      "l": 1582,
      "c": 1674,
      "v": 30200,
      "ma5": 1624.0,
      "ma25": 1665.9,
      "ma75": 1762.5,
      "ma200": 2483.2
    },
    {
      "date": "2026-06-04",
      "o": 1657,
      "h": 1663,
      "l": 1620,
      "c": 1635,
      "v": 13000,
      "ma5": 1636.6,
      "ma25": 1663.2,
      "ma75": 1741.2,
      "ma200": 2480.4
    },
    {
      "date": "2026-06-05",
      "o": 1618,
      "h": 1728,
      "l": 1618,
      "c": 1715,
      "v": 17000,
      "ma5": 1662.4,
      "ma25": 1665.7,
      "ma75": 1723.4,
      "ma200": 2477.8
    },
    {
      "date": "2026-06-08",
      "o": 1675,
      "h": 1708,
      "l": 1635,
      "c": 1643,
      "v": 11300,
      "ma5": 1662.0,
      "ma25": 1665.9,
      "ma75": 1714.0,
      "ma200": 2475.1
    },
    {
      "date": "2026-06-09",
      "o": 1643,
      "h": 1668,
      "l": 1635,
      "c": 1635,
      "v": 6300,
      "ma5": 1660.4,
      "ma25": 1666.6,
      "ma75": 1708.8,
      "ma200": 2472.1
    },
    {
      "date": "2026-06-10",
      "o": 1635,
      "h": 1665,
      "l": 1621,
      "c": 1621,
      "v": 8900,
      "ma5": 1649.8,
      "ma25": 1667.3,
      "ma75": 1703.8,
      "ma200": 2469.2
    },
    {
      "date": "2026-06-11",
      "o": 1650,
      "h": 1651,
      "l": 1614,
      "c": 1627,
      "v": 2700,
      "ma5": 1648.2,
      "ma25": 1668.1,
      "ma75": 1699.3,
      "ma200": 2466.2
    },
    {
      "date": "2026-06-12",
      "o": 1627,
      "h": 1641,
      "l": 1578,
      "c": 1588,
      "v": 30100,
      "ma5": 1622.8,
      "ma25": 1667.1,
      "ma75": 1694.7,
      "ma200": 2460.6
    },
    {
      "date": "2026-06-15",
      "o": 1628,
      "h": 1673,
      "l": 1622,
      "c": 1633,
      "v": 9800,
      "ma5": 1620.8,
      "ma25": 1666.3,
      "ma75": 1691.5,
      "ma200": 2455.3
    },
    {
      "date": "2026-06-16",
      "o": 1626,
      "h": 1642,
      "l": 1616,
      "c": 1616,
      "v": 8100,
      "ma5": 1617.0,
      "ma25": 1667.2,
      "ma75": 1689.0,
      "ma200": 2448.3
    },
    {
      "date": "2026-06-17",
      "o": 1616,
      "h": 1680,
      "l": 1616,
      "c": 1637,
      "v": 4900,
      "ma5": 1620.2,
      "ma25": 1668.0,
      "ma75": 1686.7,
      "ma200": 2441.0
    },
    {
      "date": "2026-06-18",
      "o": 1637,
      "h": 1669,
      "l": 1637,
      "c": 1669,
      "v": 3000,
      "ma5": 1628.6,
      "ma25": 1675.0,
      "ma75": 1684.7,
      "ma200": 2433.7
    },
    {
      "date": "2026-06-19",
      "o": 1635,
      "h": 1645,
      "l": 1613,
      "c": 1637,
      "v": 8800,
      "ma5": 1638.4,
      "ma25": 1671.3,
      "ma75": 1682.9,
      "ma200": 2426.2
    },
    {
      "date": "2026-06-22",
      "o": 1611,
      "h": 1678,
      "l": 1576,
      "c": 1576,
      "v": 12000,
      "ma5": 1627.0,
      "ma25": 1656.9,
      "ma75": 1681.9,
      "ma200": 2418.8
    },
    {
      "date": "2026-06-23",
      "o": 1576,
      "h": 1580,
      "l": 1544,
      "c": 1545,
      "v": 15900,
      "ma5": 1612.8,
      "ma25": 1640.6,
      "ma75": 1681.9,
      "ma200": 2411.1
    },
    {
      "date": "2026-06-24",
      "o": 1545,
      "h": 1556,
      "l": 1490,
      "c": 1506,
      "v": 33900,
      "ma5": 1586.6,
      "ma25": 1628.3,
      "ma75": 1681.4,
      "ma200": 2403.3
    },
    {
      "date": "2026-06-25",
      "o": 1525,
      "h": 1525,
      "l": 1430,
      "c": 1490,
      "v": 26200,
      "ma5": 1550.8,
      "ma25": 1618.4,
      "ma75": 1679.6,
      "ma200": 2395.8
    },
    {
      "date": "2026-06-26",
      "o": 1490,
      "h": 1495,
      "l": 1459,
      "c": 1476,
      "v": 17800,
      "ma5": 1518.6,
      "ma25": 1608.9,
      "ma75": 1676.7,
      "ma200": 2388.6
    },
    {
      "date": "2026-06-29",
      "o": 1479,
      "h": 1526,
      "l": 1479,
      "c": 1495,
      "v": 13100,
      "ma5": 1502.4,
      "ma25": 1602.6,
      "ma75": 1675.2,
      "ma200": 2381.0
    },
    {
      "date": "2026-06-30",
      "o": 1502,
      "h": 1523,
      "l": 1491,
      "c": 1497,
      "v": 11000,
      "ma5": 1492.8,
      "ma25": 1598.5,
      "ma75": 1671.9,
      "ma200": 2373.9
    }
  ]
}